README.rst
setup.py
django_print_sql/__init__.py
django_print_sql/print_sql.py
django_print_sql.egg-info/PKG-INFO
django_print_sql.egg-info/SOURCES.txt
django_print_sql.egg-info/dependency_links.txt
django_print_sql.egg-info/top_level.txt