Metadata-Version: 1.1
Name: django-print-sql
Version: 2018.3.4
Summary: django_print_sql is an easy-to-use SQL debug tool for Django developers to print SQL statements
Home-page: https://github.com/rabbit-aaron/django-print-sql
Author: Aaron Zhang
Author-email: rabbit.aaron@gmail.com
License: UNKNOWN
Keywords: django sql debug
Platform: UNKNOWN
Classifier: Development Status :: 4 - Beta
Classifier: Intended Audience :: Developers
Classifier: License :: OSI Approved :: MIT License
Classifier: Programming Language :: Python :: 2
Classifier: Programming Language :: Python :: 2.7
Classifier: Programming Language :: Python :: 3
Classifier: Programming Language :: Python :: 3.4
Classifier: Programming Language :: Python :: 3.5
Classifier: Programming Language :: Python :: 3.6
